Zhengzebiaodashi30FenzhongRumen/README.md
Zhengzebiaodashi30FenzhongRumen/__init__.py
Zhengzebiaodashi30FenzhongRumen/__main__.py
Zhengzebiaodashi30FenzhongRumen/file.epub
Zhengzebiaodashi30FenzhongRumen/index.html
Zhengzebiaodashi30FenzhongRumen/css/__init__.py
Zhengzebiaodashi30FenzhongRumen/css/annotations.css
Zhengzebiaodashi30FenzhongRumen/css/main.css
Zhengzebiaodashi30FenzhongRumen/css/normalize.css
Zhengzebiaodashi30FenzhongRumen/css/popup.css
Zhengzebiaodashi30FenzhongRumen/font/__init__.py
Zhengzebiaodashi30FenzhongRumen/font/fontello.eot
Zhengzebiaodashi30FenzhongRumen/font/fontello.svg
Zhengzebiaodashi30FenzhongRumen/font/fontello.ttf
Zhengzebiaodashi30FenzhongRumen/font/fontello.woff
Zhengzebiaodashi30FenzhongRumen/img/__init__.py
Zhengzebiaodashi30FenzhongRumen/img/annotator-glyph-sprite.png
Zhengzebiaodashi30FenzhongRumen/img/annotator-icon-sprite.png
Zhengzebiaodashi30FenzhongRumen/img/apple-touch-icon.png
Zhengzebiaodashi30FenzhongRumen/img/cancelfullscreen.png
Zhengzebiaodashi30FenzhongRumen/img/close.png
Zhengzebiaodashi30FenzhongRumen/img/fullscreen.png
Zhengzebiaodashi30FenzhongRumen/img/loader.gif
Zhengzebiaodashi30FenzhongRumen/img/menu-icon.png
Zhengzebiaodashi30FenzhongRumen/img/save.png
Zhengzebiaodashi30FenzhongRumen/img/saved.png
Zhengzebiaodashi30FenzhongRumen/img/settings-s.png
Zhengzebiaodashi30FenzhongRumen/img/settings.png
Zhengzebiaodashi30FenzhongRumen/img/star.png
Zhengzebiaodashi30FenzhongRumen/js/__init__.py
Zhengzebiaodashi30FenzhongRumen/js/epub.js
Zhengzebiaodashi30FenzhongRumen/js/epub.min.js
Zhengzebiaodashi30FenzhongRumen/js/epub.min.map
Zhengzebiaodashi30FenzhongRumen/js/hooks.min.js
Zhengzebiaodashi30FenzhongRumen/js/hooks.min.map
Zhengzebiaodashi30FenzhongRumen/js/reader.js
Zhengzebiaodashi30FenzhongRumen/js/reader.js.map
Zhengzebiaodashi30FenzhongRumen/js/reader.min.js
Zhengzebiaodashi30FenzhongRumen/js/reader.min.map
Zhengzebiaodashi30FenzhongRumen/js/hooks/__init__.py
zhengzebiaodashi_30_fenzhong_rumen-2024.3.2.0.dist-info/METADATA
zhengzebiaodashi_30_fenzhong_rumen-2024.3.2.0.dist-info/WHEEL
zhengzebiaodashi_30_fenzhong_rumen-2024.3.2.0.dist-info/entry_points.txt
zhengzebiaodashi_30_fenzhong_rumen-2024.3.2.0.dist-info/top_level.txt
zhengzebiaodashi_30_fenzhong_rumen-2024.3.2.0.dist-info/RECORD
